<?xml version="1.0" encoding="utf-8" standalone="yes"?>
<CGProfiles>
  <StartupProfile />
  <Profiles>
    <Profile>
      <Name>CG_Beep</Name>
      <Frozen>false</Frozen>
      <RequireHome>false</RequireHome>
      <API>OpenVR</API>
      <WaveOutDeviceSource>Windows</WaveOutDeviceSource>
      <WaveOutDeviceName />
      <ManualFOV>
        <FOV>
          <Y_Top>1</Y_Top>
          <Y_Bottom>-1</Y_Bottom>
          <X_Left>-1</X_Left>
          <X_Right>1</X_Right>
          <X_Diag1>0</X_Diag1>
          <Y_Diag1>0</Y_Diag1>
          <X_Diag2>0</X_Diag2>
          <Y_Diag2>0</Y_Diag2>
          <Z>1</Z>
          <DiagCompensation>0</DiagCompensation>
          <VisiblePixelsCompensation>0</VisiblePixelsCompensation>
        </FOV>
      </ManualFOV>
      <UseManualFOV>false</UseManualFOV>
      <ResetOnMount>false</ResetOnMount>
      <PlayMountingSound>false</PlayMountingSound>
      <MountingSound>
        <CGActionWaveFile>
          <Wave>\default\sounds\CG_Jingle.cga</Wave>
          <Pan>0</Pan>
          <Volume>0</Volume>
          <LoopCount>1</LoopCount>
        </CGActionWaveFile>
      </MountingSound>
      <MountingOverlay>
        <CGActionOverlay>
          <Enabled>true</Enabled>
          <Image>\default\images\CGP_Splash.png</Image>
          <FlipHorizontal>false</FlipHorizontal>
          <FlipVertical>false</FlipVertical>
          <X>0.0477971</X>
          <Y>-0.2394423</Y>
          <Z>-0.5338967</Z>
          <Opacity>1</Opacity>
          <Width>0.2771666</Width>
          <Blink>false</Blink>
          <ShowUntilParentCalls>false</ShowUntilParentCalls>
          <TimeOut>3</TimeOut>
        </CGActionOverlay>
      </MountingOverlay>
      <PlayAreaWidth>1</PlayAreaWidth>
      <PlayAreaLength>1</PlayAreaLength>
      <Actions>
        <TriggeredAction>
          <Trigger>
            <TriggeringEvent>ResetPosition</TriggeringEvent>
            <FireLimitPerZero>0</FireLimitPerZero>
            <RotationCondition>
              <TargetRotationSide>Either</TargetRotationSide>
              <CompOperator>EqualOrGreaterThan</CompOperator>
              <TargetHalfTurns>0</TargetHalfTurns>
              <TargetHalfTurnsMax>99</TargetHalfTurnsMax>
              <TargetAccumulation>Either</TargetAccumulation>
              <TargetPeakHalfTurns>3</TargetPeakHalfTurns>
            </RotationCondition>
          </Trigger>
          <CGActionWaveFile>
            <Wave>\default\sounds\CG_AllClear.cga</Wave>
            <Pan>0</Pan>
            <Volume>14</Volume>
            <LoopCount>1</LoopCount>
          </CGActionWaveFile>
          <CGActionOverlay>
            <Enabled>false</Enabled>
            <Image>\default\images\CGP_Splash.png</Image>
            <FlipHorizontal>false</FlipHorizontal>
            <FlipVertical>false</FlipVertical>
            <X>0.0477971</X>
            <Y>-0.2394423</Y>
            <Z>-0.5338967</Z>
            <Opacity>1</Opacity>
            <Width>0.2771666</Width>
            <Blink>false</Blink>
            <ShowUntilParentCalls>false</ShowUntilParentCalls>
            <TimeOut>3</TimeOut>
          </CGActionOverlay>
        </TriggeredAction>
        <TriggeredAction>
          <Trigger>
            <TriggeringEvent>Yaw0Yaw180</TriggeringEvent>
            <FireLimitPerZero>0</FireLimitPerZero>
            <RotationCondition>
              <TargetRotationSide>Left</TargetRotationSide>
              <CompOperator>EqualOrGreaterThan</CompOperator>
              <TargetHalfTurns>3</TargetHalfTurns>
              <TargetHalfTurnsMax>99</TargetHalfTurnsMax>
              <TargetAccumulation>Increasing</TargetAccumulation>
              <TargetPeakHalfTurns>0</TargetPeakHalfTurns>
            </RotationCondition>
          </Trigger>
          <CGActionWaveFile>
            <Wave>\default\sounds\CG_BeepBeep.cga</Wave>
            <Pan>-100</Pan>
            <Volume>75</Volume>
            <LoopCount>1</LoopCount>
          </CGActionWaveFile>
          <CGActionOverlay>
            <Enabled>false</Enabled>
            <Image>\default\images\CGP_AlarmClock.png</Image>
            <FlipHorizontal>false</FlipHorizontal>
            <FlipVertical>false</FlipVertical>
            <X>0</X>
            <Y>0</Y>
            <Z>-1</Z>
            <Opacity>1</Opacity>
            <Width>1</Width>
            <Blink>false</Blink>
            <ShowUntilParentCalls>false</ShowUntilParentCalls>
            <TimeOut>2</TimeOut>
          </CGActionOverlay>
        </TriggeredAction>
        <TriggeredAction>
          <Trigger>
            <TriggeringEvent>Yaw0Yaw180</TriggeringEvent>
            <FireLimitPerZero>0</FireLimitPerZero>
            <RotationCondition>
              <TargetRotationSide>Right</TargetRotationSide>
              <CompOperator>EqualOrGreaterThan</CompOperator>
              <TargetHalfTurns>3</TargetHalfTurns>
              <TargetHalfTurnsMax>99</TargetHalfTurnsMax>
              <TargetAccumulation>Increasing</TargetAccumulation>
              <TargetPeakHalfTurns>0</TargetPeakHalfTurns>
            </RotationCondition>
          </Trigger>
          <CGActionWaveFile>
            <Wave>\default\sounds\CG_BeepBeep.cga</Wave>
            <Pan>100</Pan>
            <Volume>75</Volume>
            <LoopCount>1</LoopCount>
          </CGActionWaveFile>
          <CGActionOverlay>
            <Enabled>false</Enabled>
            <Image>\default\images\CGP_AlarmClock.png</Image>
            <FlipHorizontal>false</FlipHorizontal>
            <FlipVertical>false</FlipVertical>
            <X>0</X>
            <Y>0</Y>
            <Z>-1</Z>
            <Opacity>1</Opacity>
            <Width>1</Width>
            <Blink>false</Blink>
            <ShowUntilParentCalls>false</ShowUntilParentCalls>
            <TimeOut>2</TimeOut>
          </CGActionOverlay>
        </TriggeredAction>
      </Actions>
      <FloorMarkers />
    </Profile>
    <Profile>
      <Name>CG_Speech</Name>
      <Frozen>false</Frozen>
      <RequireHome>false</RequireHome>
      <API>OpenVR</API>
      <WaveOutDeviceSource>Windows</WaveOutDeviceSource>
      <WaveOutDeviceName />
      <ManualFOV>
        <FOV>
          <Y_Top>1</Y_Top>
          <Y_Bottom>-1</Y_Bottom>
          <X_Left>-1</X_Left>
          <X_Right>1</X_Right>
          <X_Diag1>0</X_Diag1>
          <Y_Diag1>0</Y_Diag1>
          <X_Diag2>0</X_Diag2>
          <Y_Diag2>0</Y_Diag2>
          <Z>1</Z>
          <DiagCompensation>0</DiagCompensation>
          <VisiblePixelsCompensation>0</VisiblePixelsCompensation>
        </FOV>
      </ManualFOV>
      <UseManualFOV>false</UseManualFOV>
      <ResetOnMount>false</ResetOnMount>
      <PlayMountingSound>false</PlayMountingSound>
      <MountingSound>
        <CGActionWaveFile>
          <Wave>\default\sounds\CG_Jingle.cga</Wave>
          <Pan>0</Pan>
          <Volume>0</Volume>
          <LoopCount>1</LoopCount>
        </CGActionWaveFile>
      </MountingSound>
      <MountingOverlay>
        <CGActionOverlay>
          <Enabled>true</Enabled>
          <Image>\default\images\CGP_Splash.png</Image>
          <FlipHorizontal>false</FlipHorizontal>
          <FlipVertical>false</FlipVertical>
          <X>0.0477971</X>
          <Y>-0.2394423</Y>
          <Z>-0.5338967</Z>
          <Opacity>1</Opacity>
          <Width>0.2771666</Width>
          <Blink>false</Blink>
          <ShowUntilParentCalls>false</ShowUntilParentCalls>
          <TimeOut>3</TimeOut>
        </CGActionOverlay>
      </MountingOverlay>
      <PlayAreaWidth>1</PlayAreaWidth>
      <PlayAreaLength>1</PlayAreaLength>
      <Actions>
        <TriggeredAction>
          <Trigger>
            <TriggeringEvent>ResetPosition</TriggeringEvent>
            <FireLimitPerZero>0</FireLimitPerZero>
            <RotationCondition>
              <TargetRotationSide>Either</TargetRotationSide>
              <CompOperator>EqualOrGreaterThan</CompOperator>
              <TargetHalfTurns>0</TargetHalfTurns>
              <TargetHalfTurnsMax>99</TargetHalfTurnsMax>
              <TargetAccumulation>Either</TargetAccumulation>
              <TargetPeakHalfTurns>3</TargetPeakHalfTurns>
            </RotationCondition>
          </Trigger>
          <CGActionWaveFile>
            <Wave>\default\sounds\CG_AllClear.cga</Wave>
            <Pan>0</Pan>
            <Volume>14</Volume>
            <LoopCount>1</LoopCount>
          </CGActionWaveFile>
          <CGActionOverlay>
            <Enabled>false</Enabled>
            <Image>\default\images\CGP_Splash.png</Image>
            <FlipHorizontal>false</FlipHorizontal>
            <FlipVertical>false</FlipVertical>
            <X>0.0477971</X>
            <Y>-0.2394423</Y>
            <Z>-0.5338967</Z>
            <Opacity>1</Opacity>
            <Width>0.2771666</Width>
            <Blink>false</Blink>
            <ShowUntilParentCalls>false</ShowUntilParentCalls>
            <TimeOut>3</TimeOut>
          </CGActionOverlay>
        </TriggeredAction>
        <TriggeredAction>
          <Trigger>
            <TriggeringEvent>Yaw0Yaw180</TriggeringEvent>
            <FireLimitPerZero>0</FireLimitPerZero>
            <RotationCondition>
              <TargetRotationSide>Left</TargetRotationSide>
              <CompOperator>EqualOrGreaterThan</CompOperator>
              <TargetHalfTurns>3</TargetHalfTurns>
              <TargetHalfTurnsMax>99</TargetHalfTurnsMax>
              <TargetAccumulation>Increasing</TargetAccumulation>
              <TargetPeakHalfTurns>0</TargetPeakHalfTurns>
            </RotationCondition>
          </Trigger>
          <CGActionWaveFile>
            <Wave>\default\sounds\CG_TurnRight.cga</Wave>
            <Pan>50</Pan>
            <Volume>75</Volume>
            <LoopCount>1</LoopCount>
          </CGActionWaveFile>
          <CGActionOverlay>
            <Enabled>false</Enabled>
            <Image>\default\images\CGP_AlarmClock.png</Image>
            <FlipHorizontal>false</FlipHorizontal>
            <FlipVertical>false</FlipVertical>
            <X>0</X>
            <Y>0</Y>
            <Z>-1</Z>
            <Opacity>1</Opacity>
            <Width>1</Width>
            <Blink>false</Blink>
            <ShowUntilParentCalls>false</ShowUntilParentCalls>
            <TimeOut>2</TimeOut>
          </CGActionOverlay>
        </TriggeredAction>
        <TriggeredAction>
          <Trigger>
            <TriggeringEvent>Yaw0Yaw180</TriggeringEvent>
            <FireLimitPerZero>0</FireLimitPerZero>
            <RotationCondition>
              <TargetRotationSide>Right</TargetRotationSide>
              <CompOperator>EqualOrGreaterThan</CompOperator>
              <TargetHalfTurns>3</TargetHalfTurns>
              <TargetHalfTurnsMax>99</TargetHalfTurnsMax>
              <TargetAccumulation>Increasing</TargetAccumulation>
              <TargetPeakHalfTurns>0</TargetPeakHalfTurns>
            </RotationCondition>
          </Trigger>
          <CGActionWaveFile>
            <Wave>\default\sounds\CG_TurnLeft.cga</Wave>
            <Pan>-50</Pan>
            <Volume>75</Volume>
            <LoopCount>1</LoopCount>
          </CGActionWaveFile>
          <CGActionOverlay>
            <Enabled>false</Enabled>
            <Image>\default\images\CGP_AlarmClock.png</Image>
            <FlipHorizontal>false</FlipHorizontal>
            <FlipVertical>false</FlipVertical>
            <X>0</X>
            <Y>0</Y>
            <Z>-1</Z>
            <Opacity>1</Opacity>
            <Width>1</Width>
            <Blink>false</Blink>
            <ShowUntilParentCalls>false</ShowUntilParentCalls>
            <TimeOut>2</TimeOut>
          </CGActionOverlay>
        </TriggeredAction>
      </Actions>
      <FloorMarkers />
    </Profile>
    <Profile>
      <Name>CGP_Arcade</Name>
      <Frozen>false</Frozen>
      <RequireHome>false</RequireHome>
      <API>OpenVR</API>
      <WaveOutDeviceSource>Windows</WaveOutDeviceSource>
      <WaveOutDeviceName />
      <ManualFOV>
        <FOV>
          <Y_Top>1</Y_Top>
          <Y_Bottom>-1</Y_Bottom>
          <X_Left>-1</X_Left>
          <X_Right>1</X_Right>
          <X_Diag1>0</X_Diag1>
          <Y_Diag1>0</Y_Diag1>
          <X_Diag2>0</X_Diag2>
          <Y_Diag2>0</Y_Diag2>
          <Z>1</Z>
          <DiagCompensation>0</DiagCompensation>
          <VisiblePixelsCompensation>0</VisiblePixelsCompensation>
        </FOV>
      </ManualFOV>
      <UseManualFOV>false</UseManualFOV>
      <ResetOnMount>false</ResetOnMount>
      <PlayMountingSound>true</PlayMountingSound>
      <MountingSound>
        <CGActionWaveFile>
          <Wave>\default\sounds\CG_Jingle.cga</Wave>
          <Pan>0</Pan>
          <Volume>0</Volume>
          <LoopCount>1</LoopCount>
        </CGActionWaveFile>
      </MountingSound>
      <MountingOverlay>
        <CGActionOverlay>
          <Enabled>true</Enabled>
          <Image>\default\images\CGP_Splash.png</Image>
          <FlipHorizontal>false</FlipHorizontal>
          <FlipVertical>false</FlipVertical>
          <X>0.0477971</X>
          <Y>-0.2394423</Y>
          <Z>-0.5338967</Z>
          <Opacity>1</Opacity>
          <Width>0.2771666</Width>
          <Blink>false</Blink>
          <ShowUntilParentCalls>false</ShowUntilParentCalls>
          <TimeOut>3</TimeOut>
        </CGActionOverlay>
      </MountingOverlay>
      <PlayAreaWidth>1</PlayAreaWidth>
      <PlayAreaLength>1</PlayAreaLength>
      <Actions>
        <TriggeredAction>
          <Trigger>
            <TriggeringEvent>ResetPosition</TriggeringEvent>
            <FireLimitPerZero>0</FireLimitPerZero>
            <RotationCondition>
              <TargetRotationSide>Either</TargetRotationSide>
              <CompOperator>EqualOrGreaterThan</CompOperator>
              <TargetHalfTurns>0</TargetHalfTurns>
              <TargetHalfTurnsMax>99</TargetHalfTurnsMax>
              <TargetAccumulation>Either</TargetAccumulation>
              <TargetPeakHalfTurns>3</TargetPeakHalfTurns>
            </RotationCondition>
          </Trigger>
          <CGActionWaveFile>
            <Wave>\default\sounds\CGP_Bling.cga</Wave>
            <Pan>0</Pan>
            <Volume>50</Volume>
            <LoopCount>1</LoopCount>
          </CGActionWaveFile>
          <CGActionOverlay>
            <Enabled>true</Enabled>
            <Image>\default\images\CGP_ArcadeClear.png</Image>
            <FlipHorizontal>false</FlipHorizontal>
            <FlipVertical>false</FlipVertical>
            <X>-0.008149388</X>
            <Y>-0.2204541</Y>
            <Z>-0.6892004</Z>
            <Opacity>1</Opacity>
            <Width>0.3534209</Width>
            <Blink>false</Blink>
            <ShowUntilParentCalls>false</ShowUntilParentCalls>
            <TimeOut>1.7</TimeOut>
          </CGActionOverlay>
        </TriggeredAction>
        <TriggeredAction>
          <Trigger>
            <TriggeringEvent>Yaw0Yaw180</TriggeringEvent>
            <FireLimitPerZero>1</FireLimitPerZero>
            <RotationCondition>
              <TargetRotationSide>Left</TargetRotationSide>
              <CompOperator>EqualOrGreaterThan</CompOperator>
              <TargetHalfTurns>3</TargetHalfTurns>
              <TargetHalfTurnsMax>99</TargetHalfTurnsMax>
              <TargetAccumulation>Increasing</TargetAccumulation>
              <TargetPeakHalfTurns>0</TargetPeakHalfTurns>
            </RotationCondition>
          </Trigger>
          <CGActionWaveFile>
            <Wave>\default\sounds\CGP_Notif05.cga</Wave>
            <Pan>0</Pan>
            <Volume>75</Volume>
            <LoopCount>1</LoopCount>
          </CGActionWaveFile>
          <CGActionOverlay>
            <Enabled>true</Enabled>
            <Image>\default\images\CGP_ArcadeRight.png</Image>
            <FlipHorizontal>false</FlipHorizontal>
            <FlipVertical>false</FlipVertical>
            <X>-0.016312</X>
            <Y>-0.2124614</Y>
            <Z>-0.688656</Z>
            <Opacity>1</Opacity>
            <Width>0.3550784</Width>
            <Blink>false</Blink>
            <ShowUntilParentCalls>false</ShowUntilParentCalls>
            <TimeOut>0</TimeOut>
          </CGActionOverlay>
        </TriggeredAction>
        <TriggeredAction>
          <Trigger>
            <TriggeringEvent>Yaw0Yaw180</TriggeringEvent>
            <FireLimitPerZero>1</FireLimitPerZero>
            <RotationCondition>
              <TargetRotationSide>Right</TargetRotationSide>
              <CompOperator>EqualOrGreaterThan</CompOperator>
              <TargetHalfTurns>3</TargetHalfTurns>
              <TargetHalfTurnsMax>99</TargetHalfTurnsMax>
              <TargetAccumulation>Increasing</TargetAccumulation>
              <TargetPeakHalfTurns>0</TargetPeakHalfTurns>
            </RotationCondition>
          </Trigger>
          <CGActionWaveFile>
            <Wave>\default\sounds\CGP_Notif05.cga</Wave>
            <Pan>0</Pan>
            <Volume>75</Volume>
            <LoopCount>1</LoopCount>
          </CGActionWaveFile>
          <CGActionOverlay>
            <Enabled>true</Enabled>
            <Image>\default\images\CGP_ArcadeLeft.png</Image>
            <FlipHorizontal>false</FlipHorizontal>
            <FlipVertical>false</FlipVertical>
            <X>-0.016312</X>
            <Y>-0.2124614</Y>
            <Z>-0.688656</Z>
            <Opacity>1</Opacity>
            <Width>0.3550784</Width>
            <Blink>false</Blink>
            <ShowUntilParentCalls>false</ShowUntilParentCalls>
            <TimeOut>0</TimeOut>
          </CGActionOverlay>
        </TriggeredAction>
        <TriggeredAction>
          <Trigger>
            <TriggeringEvent>Yaw0Yaw180</TriggeringEvent>
            <FireLimitPerZero>1</FireLimitPerZero>
            <RotationCondition>
              <TargetRotationSide>Either</TargetRotationSide>
              <CompOperator>EqualOrGreaterThan</CompOperator>
              <TargetHalfTurns>4</TargetHalfTurns>
              <TargetHalfTurnsMax>99</TargetHalfTurnsMax>
              <TargetAccumulation>Increasing</TargetAccumulation>
              <TargetPeakHalfTurns>0</TargetPeakHalfTurns>
            </RotationCondition>
          </Trigger>
          <CGActionWaveFile>
            <Wave>\default\sounds\CGP_Negative02.cga</Wave>
            <Pan>0</Pan>
            <Volume>50</Volume>
            <LoopCount>1</LoopCount>
          </CGActionWaveFile>
          <CGActionOverlay>
            <Enabled>true</Enabled>
            <Image>\default\images\CGP_Dimmer.png</Image>
            <FlipHorizontal>false</FlipHorizontal>
            <FlipVertical>false</FlipVertical>
            <X>-0.01456999</X>
            <Y>-0.08824251</Y>
            <Z>-0.8311739</Z>
            <Opacity>1</Opacity>
            <Width>7.685575</Width>
            <Blink>false</Blink>
            <ShowUntilParentCalls>false</ShowUntilParentCalls>
            <TimeOut>0</TimeOut>
          </CGActionOverlay>
        </TriggeredAction>
      </Actions>
      <FloorMarkers>
        <FloorMarker>
          <Enabled>false</Enabled>
          <Image>\default\images\CGP_CenterCircle.png</Image>
          <FlipHorizontal>false</FlipHorizontal>
          <FlipVertical>false</FlipVertical>
          <X>0</X>
          <Y>0</Y>
          <Z>0</Z>
          <Opacity>1</Opacity>
          <Width>0.6</Width>
          <Blink>false</Blink>
          <ShowUntilParentCalls>false</ShowUntilParentCalls>
          <TimeOut>2</TimeOut>
          <Description>Center Marker</Description>
          <AreaBufferX>0.4</AreaBufferX>
          <AreaBufferY>0.4</AreaBufferY>
          <ShowWhenHmdInside>true</ShowWhenHmdInside>
          <ShowWhenHmdOutside>true</ShowWhenHmdOutside>
          <NotifyOnHmdEntry>false</NotifyOnHmdEntry>
          <NotifyOnHmdDeparture>false</NotifyOnHmdDeparture>
          <EntryWaveAction>
            <CGActionWaveFile>
              <Wave>\default\sounds\CGP_Bling.cga</Wave>
              <Pan>0</Pan>
              <Volume>30</Volume>
              <LoopCount>1</LoopCount>
            </CGActionWaveFile>
          </EntryWaveAction>
          <EntryOverlay>
            <CGActionOverlay>
              <Enabled>false</Enabled>
              <Image>\default\images\CGP_Splash.png</Image>
              <FlipHorizontal>false</FlipHorizontal>
              <FlipVertical>false</FlipVertical>
              <X>0.0477971</X>
              <Y>-0.2394423</Y>
              <Z>-0.5338967</Z>
              <Opacity>1</Opacity>
              <Width>0.2771666</Width>
              <Blink>false</Blink>
              <ShowUntilParentCalls>false</ShowUntilParentCalls>
              <TimeOut>3</TimeOut>
            </CGActionOverlay>
          </EntryOverlay>
          <DepartureWaveAction>
            <CGActionWaveFile>
              <Wave>\default\sounds\CGP_Click01.cga</Wave>
              <Pan>0</Pan>
              <Volume>100</Volume>
              <LoopCount>1</LoopCount>
            </CGActionWaveFile>
          </DepartureWaveAction>
          <DepartureOverlay>
            <CGActionOverlay>
              <Enabled>true</Enabled>
              <Image>\default\images\CGP_Caution.png</Image>
              <FlipHorizontal>false</FlipHorizontal>
              <FlipVertical>false</FlipVertical>
              <X>-0.01456082</X>
              <Y>-0.2598561</Y>
              <Z>-0.4304725</Z>
              <Opacity>1</Opacity>
              <Width>0.1115511</Width>
              <Blink>false</Blink>
              <ShowUntilParentCalls>true</ShowUntilParentCalls>
              <TimeOut>3</TimeOut>
            </CGActionOverlay>
          </DepartureOverlay>
        </FloorMarker>
      </FloorMarkers>
    </Profile>
    <Profile>
      <Name>CGP_HotEdge</Name>
      <Frozen>false</Frozen>
      <RequireHome>false</RequireHome>
      <API>OpenVR</API>
      <WaveOutDeviceSource>Windows</WaveOutDeviceSource>
      <WaveOutDeviceName />
      <ManualFOV>
        <FOV>
          <Y_Top>1</Y_Top>
          <Y_Bottom>-1</Y_Bottom>
          <X_Left>-1</X_Left>
          <X_Right>1</X_Right>
          <X_Diag1>0</X_Diag1>
          <Y_Diag1>0</Y_Diag1>
          <X_Diag2>0</X_Diag2>
          <Y_Diag2>0</Y_Diag2>
          <Z>1</Z>
          <DiagCompensation>0</DiagCompensation>
          <VisiblePixelsCompensation>0</VisiblePixelsCompensation>
        </FOV>
      </ManualFOV>
      <UseManualFOV>false</UseManualFOV>
      <ResetOnMount>false</ResetOnMount>
      <PlayMountingSound>true</PlayMountingSound>
      <MountingSound>
        <CGActionWaveFile>
          <Wave>\default\sounds\CG_Jingle.cga</Wave>
          <Pan>0</Pan>
          <Volume>0</Volume>
          <LoopCount>1</LoopCount>
        </CGActionWaveFile>
      </MountingSound>
      <MountingOverlay>
        <CGActionOverlay>
          <Enabled>true</Enabled>
          <Image>\default\images\CGP_Splash.png</Image>
          <FlipHorizontal>false</FlipHorizontal>
          <FlipVertical>false</FlipVertical>
          <X>0.0477971</X>
          <Y>-0.2394423</Y>
          <Z>-0.5338967</Z>
          <Opacity>1</Opacity>
          <Width>0.2771666</Width>
          <Blink>false</Blink>
          <ShowUntilParentCalls>false</ShowUntilParentCalls>
          <TimeOut>3</TimeOut>
        </CGActionOverlay>
      </MountingOverlay>
      <PlayAreaWidth>1</PlayAreaWidth>
      <PlayAreaLength>1</PlayAreaLength>
      <Actions>
        <TriggeredAction>
          <Trigger>
            <TriggeringEvent>ResetPosition</TriggeringEvent>
            <FireLimitPerZero>0</FireLimitPerZero>
            <RotationCondition>
              <TargetRotationSide>Either</TargetRotationSide>
              <CompOperator>EqualOrGreaterThan</CompOperator>
              <TargetHalfTurns>0</TargetHalfTurns>
              <TargetHalfTurnsMax>99</TargetHalfTurnsMax>
              <TargetAccumulation>Either</TargetAccumulation>
              <TargetPeakHalfTurns>3</TargetPeakHalfTurns>
            </RotationCondition>
          </Trigger>
          <CGActionWaveFile>
            <Wave>\default\sounds\CG_AllClear.cga</Wave>
            <Pan>0</Pan>
            <Volume>14</Volume>
            <LoopCount>1</LoopCount>
          </CGActionWaveFile>
          <CGActionOverlay>
            <Enabled>false</Enabled>
            <Image>\default\images\CGP_Splash.png</Image>
            <FlipHorizontal>false</FlipHorizontal>
            <FlipVertical>false</FlipVertical>
            <X>0.0477971</X>
            <Y>-0.2394423</Y>
            <Z>-0.5338967</Z>
            <Opacity>1</Opacity>
            <Width>0.2771666</Width>
            <Blink>false</Blink>
            <ShowUntilParentCalls>false</ShowUntilParentCalls>
            <TimeOut>3</TimeOut>
          </CGActionOverlay>
        </TriggeredAction>
        <TriggeredAction>
          <Trigger>
            <TriggeringEvent>Yaw0Yaw180</TriggeringEvent>
            <FireLimitPerZero>0</FireLimitPerZero>
            <RotationCondition>
              <TargetRotationSide>Left</TargetRotationSide>
              <CompOperator>EqualOrGreaterThan</CompOperator>
              <TargetHalfTurns>3</TargetHalfTurns>
              <TargetHalfTurnsMax>99</TargetHalfTurnsMax>
              <TargetAccumulation>Increasing</TargetAccumulation>
              <TargetPeakHalfTurns>0</TargetPeakHalfTurns>
            </RotationCondition>
          </Trigger>
          <CGActionWaveFile>
            <Wave>\default\sounds\CG_BeepBeep.cga</Wave>
            <Pan>-100</Pan>
            <Volume>75</Volume>
            <LoopCount>1</LoopCount>
          </CGActionWaveFile>
          <CGActionOverlay>
            <Enabled>true</Enabled>
            <Image>\default\images\CGP_HotEdge.png</Image>
            <FlipHorizontal>false</FlipHorizontal>
            <FlipVertical>false</FlipVertical>
            <X>-0.5162063</X>
            <Y>-0.04445265</Y>
            <Z>-0.3056119</Z>
            <Opacity>0.2</Opacity>
            <Width>0.5333053</Width>
            <Blink>false</Blink>
            <ShowUntilParentCalls>false</ShowUntilParentCalls>
            <TimeOut>0.2</TimeOut>
          </CGActionOverlay>
        </TriggeredAction>
        <TriggeredAction>
          <Trigger>
            <TriggeringEvent>Yaw0Yaw180</TriggeringEvent>
            <FireLimitPerZero>0</FireLimitPerZero>
            <RotationCondition>
              <TargetRotationSide>Right</TargetRotationSide>
              <CompOperator>EqualOrGreaterThan</CompOperator>
              <TargetHalfTurns>3</TargetHalfTurns>
              <TargetHalfTurnsMax>99</TargetHalfTurnsMax>
              <TargetAccumulation>Increasing</TargetAccumulation>
              <TargetPeakHalfTurns>0</TargetPeakHalfTurns>
            </RotationCondition>
          </Trigger>
          <CGActionWaveFile>
            <Wave>\default\sounds\CG_BeepBeep.cga</Wave>
            <Pan>100</Pan>
            <Volume>75</Volume>
            <LoopCount>1</LoopCount>
          </CGActionWaveFile>
          <CGActionOverlay>
            <Enabled>true</Enabled>
            <Image>\default\images\CGP_HotEdge.png</Image>
            <FlipHorizontal>false</FlipHorizontal>
            <FlipVertical>false</FlipVertical>
            <X>0.5198181</X>
            <Y>-0.04445264</Y>
            <Z>-0.3056119</Z>
            <Opacity>0.2</Opacity>
            <Width>0.5333053</Width>
            <Blink>false</Blink>
            <ShowUntilParentCalls>false</ShowUntilParentCalls>
            <TimeOut>0.2</TimeOut>
          </CGActionOverlay>
        </TriggeredAction>
      </Actions>
      <FloorMarkers>
        <FloorMarker>
          <Enabled>false</Enabled>
          <Image>\default\images\CGP_CenterCircle.png</Image>
          <FlipHorizontal>false</FlipHorizontal>
          <FlipVertical>false</FlipVertical>
          <X>0</X>
          <Y>0</Y>
          <Z>0</Z>
          <Opacity>1</Opacity>
          <Width>0.6</Width>
          <Blink>false</Blink>
          <ShowUntilParentCalls>false</ShowUntilParentCalls>
          <TimeOut>2</TimeOut>
          <Description>Center Marker</Description>
          <AreaBufferX>0.4</AreaBufferX>
          <AreaBufferY>0.4</AreaBufferY>
          <ShowWhenHmdInside>true</ShowWhenHmdInside>
          <ShowWhenHmdOutside>true</ShowWhenHmdOutside>
          <NotifyOnHmdEntry>false</NotifyOnHmdEntry>
          <NotifyOnHmdDeparture>false</NotifyOnHmdDeparture>
          <EntryWaveAction>
            <CGActionWaveFile>
              <Wave>\default\sounds\CGP_Bling.cga</Wave>
              <Pan>0</Pan>
              <Volume>30</Volume>
              <LoopCount>1</LoopCount>
            </CGActionWaveFile>
          </EntryWaveAction>
          <EntryOverlay>
            <CGActionOverlay>
              <Enabled>false</Enabled>
              <Image>\default\images\CGP_Splash.png</Image>
              <FlipHorizontal>false</FlipHorizontal>
              <FlipVertical>false</FlipVertical>
              <X>0.0477971</X>
              <Y>-0.2394423</Y>
              <Z>-0.5338967</Z>
              <Opacity>1</Opacity>
              <Width>0.2771666</Width>
              <Blink>false</Blink>
              <ShowUntilParentCalls>false</ShowUntilParentCalls>
              <TimeOut>3</TimeOut>
            </CGActionOverlay>
          </EntryOverlay>
          <DepartureWaveAction>
            <CGActionWaveFile>
              <Wave>\default\sounds\CGP_Click01.cga</Wave>
              <Pan>0</Pan>
              <Volume>100</Volume>
              <LoopCount>1</LoopCount>
            </CGActionWaveFile>
          </DepartureWaveAction>
          <DepartureOverlay>
            <CGActionOverlay>
              <Enabled>true</Enabled>
              <Image>\default\images\CGP_Caution.png</Image>
              <FlipHorizontal>false</FlipHorizontal>
              <FlipVertical>false</FlipVertical>
              <X>-0.01456082</X>
              <Y>-0.2598561</Y>
              <Z>-0.4304725</Z>
              <Opacity>1</Opacity>
              <Width>0.1115511</Width>
              <Blink>false</Blink>
              <ShowUntilParentCalls>true</ShowUntilParentCalls>
              <TimeOut>3</TimeOut>
            </CGActionOverlay>
          </DepartureOverlay>
        </FloorMarker>
      </FloorMarkers>
    </Profile>
    <Profile>
      <Name>CGP_SilentArrow</Name>
      <Frozen>false</Frozen>
      <RequireHome>false</RequireHome>
      <API>OpenVR</API>
      <WaveOutDeviceSource>Windows</WaveOutDeviceSource>
      <WaveOutDeviceName />
      <ManualFOV>
        <FOV>
          <Y_Top>1</Y_Top>
          <Y_Bottom>-1</Y_Bottom>
          <X_Left>-1</X_Left>
          <X_Right>1</X_Right>
          <X_Diag1>0</X_Diag1>
          <Y_Diag1>0</Y_Diag1>
          <X_Diag2>0</X_Diag2>
          <Y_Diag2>0</Y_Diag2>
          <Z>1</Z>
          <DiagCompensation>0</DiagCompensation>
          <VisiblePixelsCompensation>0</VisiblePixelsCompensation>
        </FOV>
      </ManualFOV>
      <UseManualFOV>false</UseManualFOV>
      <ResetOnMount>false</ResetOnMount>
      <PlayMountingSound>true</PlayMountingSound>
      <MountingSound>
        <CGActionWaveFile>
          <Wave>\default\sounds\CG_Jingle.cga</Wave>
          <Pan>0</Pan>
          <Volume>0</Volume>
          <LoopCount>1</LoopCount>
        </CGActionWaveFile>
      </MountingSound>
      <MountingOverlay>
        <CGActionOverlay>
          <Enabled>true</Enabled>
          <Image>\default\images\CGP_Splash.png</Image>
          <FlipHorizontal>false</FlipHorizontal>
          <FlipVertical>false</FlipVertical>
          <X>0.0477971</X>
          <Y>-0.2394423</Y>
          <Z>-0.5338967</Z>
          <Opacity>1</Opacity>
          <Width>0.2771666</Width>
          <Blink>false</Blink>
          <ShowUntilParentCalls>false</ShowUntilParentCalls>
          <TimeOut>3</TimeOut>
        </CGActionOverlay>
      </MountingOverlay>
      <PlayAreaWidth>1</PlayAreaWidth>
      <PlayAreaLength>1</PlayAreaLength>
      <Actions>
        <TriggeredAction>
          <Trigger>
            <TriggeringEvent>Yaw0Yaw180</TriggeringEvent>
            <FireLimitPerZero>0</FireLimitPerZero>
            <RotationCondition>
              <TargetRotationSide>Left</TargetRotationSide>
              <CompOperator>EqualOrGreaterThan</CompOperator>
              <TargetHalfTurns>3</TargetHalfTurns>
              <TargetHalfTurnsMax>99</TargetHalfTurnsMax>
              <TargetAccumulation>Increasing</TargetAccumulation>
              <TargetPeakHalfTurns>0</TargetPeakHalfTurns>
            </RotationCondition>
          </Trigger>
          <CGActionWaveFile>
            <Wave>\default\sounds\CG_TurnRight.cga</Wave>
            <Pan>50</Pan>
            <Volume>0</Volume>
            <LoopCount>1</LoopCount>
          </CGActionWaveFile>
          <CGActionOverlay>
            <Enabled>true</Enabled>
            <Image>\default\images\CGP_Arrow.png</Image>
            <FlipHorizontal>true</FlipHorizontal>
            <FlipVertical>false</FlipVertical>
            <X>-0.01153026</X>
            <Y>-0.3632032</Y>
            <Z>-0.6341644</Z>
            <Opacity>1</Opacity>
            <Width>0.1848665</Width>
            <Blink>false</Blink>
            <ShowUntilParentCalls>false</ShowUntilParentCalls>
            <TimeOut>-2</TimeOut>
          </CGActionOverlay>
        </TriggeredAction>
        <TriggeredAction>
          <Trigger>
            <TriggeringEvent>Yaw0Yaw180</TriggeringEvent>
            <FireLimitPerZero>0</FireLimitPerZero>
            <RotationCondition>
              <TargetRotationSide>Right</TargetRotationSide>
              <CompOperator>EqualOrGreaterThan</CompOperator>
              <TargetHalfTurns>3</TargetHalfTurns>
              <TargetHalfTurnsMax>99</TargetHalfTurnsMax>
              <TargetAccumulation>Increasing</TargetAccumulation>
              <TargetPeakHalfTurns>0</TargetPeakHalfTurns>
            </RotationCondition>
          </Trigger>
          <CGActionWaveFile>
            <Wave>\default\sounds\CG_TurnLeft.cga</Wave>
            <Pan>50</Pan>
            <Volume>0</Volume>
            <LoopCount>1</LoopCount>
          </CGActionWaveFile>
          <CGActionOverlay>
            <Enabled>true</Enabled>
            <Image>\default\images\CGP_Arrow.png</Image>
            <FlipHorizontal>false</FlipHorizontal>
            <FlipVertical>false</FlipVertical>
            <X>-0.01153026</X>
            <Y>-0.3632032</Y>
            <Z>-0.6341644</Z>
            <Opacity>1</Opacity>
            <Width>0.1848665</Width>
            <Blink>false</Blink>
            <ShowUntilParentCalls>false</ShowUntilParentCalls>
            <TimeOut>-2</TimeOut>
          </CGActionOverlay>
        </TriggeredAction>
      </Actions>
      <FloorMarkers>
        <FloorMarker>
          <Enabled>false</Enabled>
          <Image>\default\images\CGP_CenterCircle.png</Image>
          <FlipHorizontal>false</FlipHorizontal>
          <FlipVertical>false</FlipVertical>
          <X>0</X>
          <Y>0</Y>
          <Z>0</Z>
          <Opacity>1</Opacity>
          <Width>0.6</Width>
          <Blink>false</Blink>
          <ShowUntilParentCalls>false</ShowUntilParentCalls>
          <TimeOut>2</TimeOut>
          <Description>Center Marker</Description>
          <AreaBufferX>0.4</AreaBufferX>
          <AreaBufferY>0.4</AreaBufferY>
          <ShowWhenHmdInside>true</ShowWhenHmdInside>
          <ShowWhenHmdOutside>true</ShowWhenHmdOutside>
          <NotifyOnHmdEntry>false</NotifyOnHmdEntry>
          <NotifyOnHmdDeparture>false</NotifyOnHmdDeparture>
          <EntryWaveAction>
            <CGActionWaveFile>
              <Wave>\default\sounds\CGP_Bling.cga</Wave>
              <Pan>0</Pan>
              <Volume>30</Volume>
              <LoopCount>1</LoopCount>
            </CGActionWaveFile>
          </EntryWaveAction>
          <EntryOverlay>
            <CGActionOverlay>
              <Enabled>false</Enabled>
              <Image>\default\images\CGP_Splash.png</Image>
              <FlipHorizontal>false</FlipHorizontal>
              <FlipVertical>false</FlipVertical>
              <X>0.0477971</X>
              <Y>-0.2394423</Y>
              <Z>-0.5338967</Z>
              <Opacity>1</Opacity>
              <Width>0.2771666</Width>
              <Blink>false</Blink>
              <ShowUntilParentCalls>false</ShowUntilParentCalls>
              <TimeOut>3</TimeOut>
            </CGActionOverlay>
          </EntryOverlay>
          <DepartureWaveAction>
            <CGActionWaveFile>
              <Wave>\default\sounds\CGP_Click01.cga</Wave>
              <Pan>0</Pan>
              <Volume>100</Volume>
              <LoopCount>1</LoopCount>
            </CGActionWaveFile>
          </DepartureWaveAction>
          <DepartureOverlay>
            <CGActionOverlay>
              <Enabled>true</Enabled>
              <Image>\default\images\CGP_Caution.png</Image>
              <FlipHorizontal>false</FlipHorizontal>
              <FlipVertical>false</FlipVertical>
              <X>-0.01456082</X>
              <Y>-0.2598561</Y>
              <Z>-0.4304725</Z>
              <Opacity>1</Opacity>
              <Width>0.1115511</Width>
              <Blink>false</Blink>
              <ShowUntilParentCalls>true</ShowUntilParentCalls>
              <TimeOut>3</TimeOut>
            </CGActionOverlay>
          </DepartureOverlay>
        </FloorMarker>
      </FloorMarkers>
    </Profile>
    <Profile>
      <Name>fixture</Name>
      <Frozen>false</Frozen>
      <RequireHome>false</RequireHome>
      <API>OpenVR</API>
      <WaveOutDeviceSource>Windows</WaveOutDeviceSource>
      <WaveOutDeviceName />
      <ManualFOV>
        <FOV>
          <Y_Top>1</Y_Top>
          <Y_Bottom>-1</Y_Bottom>
          <X_Left>-1</X_Left>
          <X_Right>1</X_Right>
          <X_Diag1>0</X_Diag1>
          <Y_Diag1>0</Y_Diag1>
          <X_Diag2>0</X_Diag2>
          <Y_Diag2>0</Y_Diag2>
          <Z>1</Z>
          <DiagCompensation>0</DiagCompensation>
          <VisiblePixelsCompensation>0</VisiblePixelsCompensation>
        </FOV>
      </ManualFOV>
      <UseManualFOV>false</UseManualFOV>
      <ResetOnMount>false</ResetOnMount>
      <PlayMountingSound>true</PlayMountingSound>
      <MountingSound>
        <CGActionWaveFile>
          <Wave>\default\sounds\CG_Jingle.cga</Wave>
          <Pan>0</Pan>
          <Volume>0</Volume>
          <LoopCount>1</LoopCount>
        </CGActionWaveFile>
      </MountingSound>
      <MountingOverlay>
        <CGActionOverlay>
          <Enabled>true</Enabled>
          <Image>\default\images\CGP_Splash.png</Image>
          <FlipHorizontal>false</FlipHorizontal>
          <FlipVertical>false</FlipVertical>
          <X>0.0477971</X>
          <Y>-0.2394423</Y>
          <Z>-0.5338967</Z>
          <Opacity>1</Opacity>
          <Width>0.2771666</Width>
          <Blink>false</Blink>
          <ShowUntilParentCalls>false</ShowUntilParentCalls>
          <TimeOut>3</TimeOut>
        </CGActionOverlay>
      </MountingOverlay>
      <PlayAreaWidth>1</PlayAreaWidth>
      <PlayAreaLength>1</PlayAreaLength>
      <Actions>
        <TriggeredAction>
          <Trigger>
            <TriggeringEvent>ResetPosition</TriggeringEvent>
            <FireLimitPerZero>0</FireLimitPerZero>
            <RotationCondition>
              <TargetRotationSide>Either</TargetRotationSide>
              <CompOperator>EqualOrGreaterThan</CompOperator>
              <TargetHalfTurns>0</TargetHalfTurns>
              <TargetHalfTurnsMax>99</TargetHalfTurnsMax>
              <TargetAccumulation>Either</TargetAccumulation>
              <TargetPeakHalfTurns>3</TargetPeakHalfTurns>
            </RotationCondition>
          </Trigger>
          <CGActionWaveFile>
            <Wave>\default\sounds\CG_AllClear.cga</Wave>
            <Pan>0</Pan>
            <Volume>14</Volume>
            <LoopCount>1</LoopCount>
          </CGActionWaveFile>
          <CGActionOverlay>
            <Enabled>false</Enabled>
            <Image>\default\images\CGP_Splash.png</Image>
            <FlipHorizontal>false</FlipHorizontal>
            <FlipVertical>false</FlipVertical>
            <X>0.0477971</X>
            <Y>-0.2394423</Y>
            <Z>-0.5338967</Z>
            <Opacity>1</Opacity>
            <Width>0.2771666</Width>
            <Blink>false</Blink>
            <ShowUntilParentCalls>false</ShowUntilParentCalls>
            <TimeOut>3</TimeOut>
          </CGActionOverlay>
        </TriggeredAction>
        <TriggeredAction>
          <Trigger>
            <TriggeringEvent>Yaw0Yaw180</TriggeringEvent>
            <FireLimitPerZero>0</FireLimitPerZero>
            <RotationCondition>
              <TargetRotationSide>Left</TargetRotationSide>
              <CompOperator>EqualOrGreaterThan</CompOperator>
              <TargetHalfTurns>3</TargetHalfTurns>
              <TargetHalfTurnsMax>99</TargetHalfTurnsMax>
              <TargetAccumulation>Increasing</TargetAccumulation>
              <TargetPeakHalfTurns>0</TargetPeakHalfTurns>
            </RotationCondition>
          </Trigger>
          <CGActionWaveFile>
            <Wave>\default\sounds\CG_BeepBeep.cga</Wave>
            <Pan>-100</Pan>
            <Volume>75</Volume>
            <LoopCount>1</LoopCount>
          </CGActionWaveFile>
          <CGActionOverlay>
            <Enabled>true</Enabled>
            <Image>\default\images\CGP_HotEdge.png</Image>
            <FlipHorizontal>false</FlipHorizontal>
            <FlipVertical>false</FlipVertical>
            <X>-0.5162063</X>
            <Y>-0.04445265</Y>
            <Z>-0.3056119</Z>
            <Opacity>0.2</Opacity>
            <Width>0.5333053</Width>
            <Blink>false</Blink>
            <ShowUntilParentCalls>false</ShowUntilParentCalls>
            <TimeOut>0.2</TimeOut>
          </CGActionOverlay>
        </TriggeredAction>
        <TriggeredAction>
          <Trigger>
            <TriggeringEvent>Yaw0Yaw180</TriggeringEvent>
            <FireLimitPerZero>0</FireLimitPerZero>
            <RotationCondition>
              <TargetRotationSide>Right</TargetRotationSide>
              <CompOperator>EqualOrGreaterThan</CompOperator>
              <TargetHalfTurns>3</TargetHalfTurns>
              <TargetHalfTurnsMax>99</TargetHalfTurnsMax>
              <TargetAccumulation>Increasing</TargetAccumulation>
              <TargetPeakHalfTurns>0</TargetPeakHalfTurns>
            </RotationCondition>
          </Trigger>
          <CGActionWaveFile>
            <Wave>\default\sounds\CG_BeepBeep.cga</Wave>
            <Pan>100</Pan>
            <Volume>75</Volume>
            <LoopCount>1</LoopCount>
          </CGActionWaveFile>
          <CGActionOverlay>
            <Enabled>true</Enabled>
            <Image>\default\images\CGP_HotEdge.png</Image>
            <FlipHorizontal>false</FlipHorizontal>
            <FlipVertical>false</FlipVertical>
            <X>0.5198181</X>
            <Y>-0.04445264</Y>
            <Z>-0.3056119</Z>
            <Opacity>0.2</Opacity>
            <Width>0.5333053</Width>
            <Blink>false</Blink>
            <ShowUntilParentCalls>false</ShowUntilParentCalls>
            <TimeOut>0.2</TimeOut>
          </CGActionOverlay>
        </TriggeredAction>
      </Actions>
      <FloorMarkers>
        <FloorMarker>
          <Enabled>true</Enabled>
          <Image>\default\images\CGP_CenterCircle.png</Image>
          <FlipHorizontal>false</FlipHorizontal>
          <FlipVertical>false</FlipVertical>
          <X>0</X>
          <Y>0</Y>
          <Z>0</Z>
          <Opacity>0.05</Opacity>
          <Width>0.1</Width>
          <Blink>false</Blink>
          <ShowUntilParentCalls>false</ShowUntilParentCalls>
          <TimeOut>2</TimeOut>
          <Description>Center Marker</Description>
          <AreaBufferX>0.4</AreaBufferX>
          <AreaBufferY>0.4</AreaBufferY>
          <ShowWhenHmdInside>true</ShowWhenHmdInside>
          <ShowWhenHmdOutside>true</ShowWhenHmdOutside>
          <NotifyOnHmdEntry>false</NotifyOnHmdEntry>
          <NotifyOnHmdDeparture>false</NotifyOnHmdDeparture>
          <EntryWaveAction>
            <CGActionWaveFile>
              <Wave>\default\sounds\CGP_Bling.cga</Wave>
              <Pan>0</Pan>
              <Volume>30</Volume>
              <LoopCount>1</LoopCount>
            </CGActionWaveFile>
          </EntryWaveAction>
          <EntryOverlay>
            <CGActionOverlay>
              <Enabled>false</Enabled>
              <Image>\default\images\CGP_Splash.png</Image>
              <FlipHorizontal>false</FlipHorizontal>
              <FlipVertical>false</FlipVertical>
              <X>0.0477971</X>
              <Y>-0.2394423</Y>
              <Z>-0.5338967</Z>
              <Opacity>1</Opacity>
              <Width>0.2771666</Width>
              <Blink>false</Blink>
              <ShowUntilParentCalls>false</ShowUntilParentCalls>
              <TimeOut>3</TimeOut>
            </CGActionOverlay>
          </EntryOverlay>
          <DepartureWaveAction>
            <CGActionWaveFile>
              <Wave>\default\sounds\CGP_Click01.cga</Wave>
              <Pan>0</Pan>
              <Volume>100</Volume>
              <LoopCount>1</LoopCount>
            </CGActionWaveFile>
          </DepartureWaveAction>
          <DepartureOverlay>
            <CGActionOverlay>
              <Enabled>true</Enabled>
              <Image>\default\images\CGP_Caution.png</Image>
              <FlipHorizontal>false</FlipHorizontal>
              <FlipVertical>false</FlipVertical>
              <X>-0.01456082</X>
              <Y>-0.2598561</Y>
              <Z>-0.4304725</Z>
              <Opacity>1</Opacity>
              <Width>0.1115511</Width>
              <Blink>false</Blink>
              <ShowUntilParentCalls>true</ShowUntilParentCalls>
              <TimeOut>3</TimeOut>
            </CGActionOverlay>
          </DepartureOverlay>
        </FloorMarker>
        <FloorMarker>
          <Enabled>true</Enabled>
          <Image>\default\images\CGP_CenterBright.png</Image>
          <FlipHorizontal>false</FlipHorizontal>
          <FlipVertical>true</FlipVertical>
          <X>0.76</X>
          <Y>0.4</Y>
          <Z>-0.14</Z>
          <Opacity>0.05</Opacity>
          <Width>1.21</Width>
          <Blink>false</Blink>
          <ShowUntilParentCalls>false</ShowUntilParentCalls>
          <TimeOut>2</TimeOut>
          <Description>simchair</Description>
          <AreaBufferX>0</AreaBufferX>
          <AreaBufferY>0</AreaBufferY>
          <ShowWhenHmdInside>false</ShowWhenHmdInside>
          <ShowWhenHmdOutside>true</ShowWhenHmdOutside>
          <NotifyOnHmdEntry>true</NotifyOnHmdEntry>
          <NotifyOnHmdDeparture>true</NotifyOnHmdDeparture>
          <EntryWaveAction>
            <CGActionWaveFile>
              <Wave>\default\sounds\CGP_Zap.cga</Wave>
              <Pan>0</Pan>
              <Volume>50</Volume>
              <LoopCount>1</LoopCount>
            </CGActionWaveFile>
          </EntryWaveAction>
          <EntryOverlay>
            <CGActionOverlay>
              <Enabled>false</Enabled>
              <Image>\default\images\CGP_AlarmClock.png</Image>
              <FlipHorizontal>false</FlipHorizontal>
              <FlipVertical>false</FlipVertical>
              <X>0</X>
              <Y>0</Y>
              <Z>-1</Z>
              <Opacity>1</Opacity>
              <Width>1</Width>
              <Blink>false</Blink>
              <ShowUntilParentCalls>false</ShowUntilParentCalls>
              <TimeOut>2</TimeOut>
            </CGActionOverlay>
          </EntryOverlay>
          <DepartureWaveAction>
            <CGActionWaveFile>
              <Wave>\default\sounds\CGP_Harsh.cga</Wave>
              <Pan>0</Pan>
              <Volume>50</Volume>
              <LoopCount>1</LoopCount>
            </CGActionWaveFile>
          </DepartureWaveAction>
          <DepartureOverlay>
            <CGActionOverlay>
              <Enabled>false</Enabled>
              <Image>\default\images\CGP_AlarmClock.png</Image>
              <FlipHorizontal>false</FlipHorizontal>
              <FlipVertical>false</FlipVertical>
              <X>0</X>
              <Y>0</Y>
              <Z>-1</Z>
              <Opacity>1</Opacity>
              <Width>1</Width>
              <Blink>false</Blink>
              <ShowUntilParentCalls>false</ShowUntilParentCalls>
              <TimeOut>2</TimeOut>
            </CGActionOverlay>
          </DepartureOverlay>
        </FloorMarker>
        <FloorMarker>
          <Enabled>true</Enabled>
          <Image>\default\images\CGP_CenterCircle.png</Image>
          <FlipHorizontal>true</FlipHorizontal>
          <FlipVertical>true</FlipVertical>
          <X>-0.8</X>
          <Y>0</Y>
          <Z>0.56</Z>
          <Opacity>0.05</Opacity>
          <Width>1.5</Width>
          <Blink>false</Blink>
          <ShowUntilParentCalls>false</ShowUntilParentCalls>
          <TimeOut>2</TimeOut>
          <Description>emptyOpt1</Description>
          <AreaBufferX>0</AreaBufferX>
          <AreaBufferY>0</AreaBufferY>
          <ShowWhenHmdInside>true</ShowWhenHmdInside>
          <ShowWhenHmdOutside>false</ShowWhenHmdOutside>
          <NotifyOnHmdEntry>true</NotifyOnHmdEntry>
          <NotifyOnHmdDeparture>true</NotifyOnHmdDeparture>
          <EntryWaveAction>
            <CGActionWaveFile>
              <Wave>\default\sounds\CGP_Zap.cga</Wave>
              <Pan>0</Pan>
              <Volume>50</Volume>
              <LoopCount>1</LoopCount>
            </CGActionWaveFile>
          </EntryWaveAction>
          <EntryOverlay>
            <CGActionOverlay>
              <Enabled>false</Enabled>
              <Image>\default\images\CGP_AlarmClock.png</Image>
              <FlipHorizontal>false</FlipHorizontal>
              <FlipVertical>false</FlipVertical>
              <X>0</X>
              <Y>0</Y>
              <Z>-1</Z>
              <Opacity>1</Opacity>
              <Width>1</Width>
              <Blink>false</Blink>
              <ShowUntilParentCalls>false</ShowUntilParentCalls>
              <TimeOut>2</TimeOut>
            </CGActionOverlay>
          </EntryOverlay>
          <DepartureWaveAction>
            <CGActionWaveFile>
              <Wave>\default\sounds\CGP_Harsh.cga</Wave>
              <Pan>0</Pan>
              <Volume>50</Volume>
              <LoopCount>1</LoopCount>
            </CGActionWaveFile>
          </DepartureWaveAction>
          <DepartureOverlay>
            <CGActionOverlay>
              <Enabled>false</Enabled>
              <Image>\default\images\CGP_AlarmClock.png</Image>
              <FlipHorizontal>false</FlipHorizontal>
              <FlipVertical>false</FlipVertical>
              <X>0</X>
              <Y>0</Y>
              <Z>-1</Z>
              <Opacity>1</Opacity>
              <Width>1</Width>
              <Blink>false</Blink>
              <ShowUntilParentCalls>false</ShowUntilParentCalls>
              <TimeOut>2</TimeOut>
            </CGActionOverlay>
          </DepartureOverlay>
        </FloorMarker>
        <FloorMarker>
          <Enabled>true</Enabled>
          <Image>\default\images\CGP_HotEdge.png</Image>
          <FlipHorizontal>false</FlipHorizontal>
          <FlipVertical>false</FlipVertical>
          <X>0.76</X>
          <Y>-0.15</Y>
          <Z>1.15</Z>
          <Opacity>0.01</Opacity>
          <Width>0.05</Width>
          <Blink>false</Blink>
          <ShowUntilParentCalls>false</ShowUntilParentCalls>
          <TimeOut>2</TimeOut>
          <Description>forward</Description>
          <AreaBufferX>0</AreaBufferX>
          <AreaBufferY>0</AreaBufferY>
          <ShowWhenHmdInside>true</ShowWhenHmdInside>
          <ShowWhenHmdOutside>true</ShowWhenHmdOutside>
          <NotifyOnHmdEntry>false</NotifyOnHmdEntry>
          <NotifyOnHmdDeparture>false</NotifyOnHmdDeparture>
          <EntryWaveAction>
            <CGActionWaveFile>
              <Wave>\default\sounds\CG_AllClear.cga</Wave>
              <Pan>0</Pan>
              <Volume>50</Volume>
              <LoopCount>1</LoopCount>
            </CGActionWaveFile>
          </EntryWaveAction>
          <EntryOverlay>
            <CGActionOverlay>
              <Enabled>false</Enabled>
              <Image />
              <FlipHorizontal>false</FlipHorizontal>
              <FlipVertical>false</FlipVertical>
              <X>0</X>
              <Y>0</Y>
              <Z>-1</Z>
              <Opacity>1</Opacity>
              <Width>1</Width>
              <Blink>false</Blink>
              <ShowUntilParentCalls>false</ShowUntilParentCalls>
              <TimeOut>2</TimeOut>
            </CGActionOverlay>
          </EntryOverlay>
          <DepartureWaveAction>
            <CGActionWaveFile>
              <Wave>\default\sounds\CG_BeepBeep.cga</Wave>
              <Pan>0</Pan>
              <Volume>50</Volume>
              <LoopCount>1</LoopCount>
            </CGActionWaveFile>
          </DepartureWaveAction>
          <DepartureOverlay>
            <CGActionOverlay>
              <Enabled>false</Enabled>
              <Image />
              <FlipHorizontal>false</FlipHorizontal>
              <FlipVertical>false</FlipVertical>
              <X>0</X>
              <Y>0</Y>
              <Z>-1</Z>
              <Opacity>1</Opacity>
              <Width>1</Width>
              <Blink>false</Blink>
              <ShowUntilParentCalls>false</ShowUntilParentCalls>
              <TimeOut>2</TimeOut>
            </CGActionOverlay>
          </DepartureOverlay>
        </FloorMarker>
      </FloorMarkers>
    </Profile>
  </Profiles>
</CGProfiles>